{"kind":"APIResourceList","apiVersion":"v1","groupVersion":"secrets.infisical.com/v1alpha1","resources":[{"name":"clustergenerators","singularName":"clustergenerator","namespaced":false,"group":"secrets.infisical.com","version":"v1alpha1","kind":"ClusterGenerator","verbs":["delete","deletecollection","get","list","patch","create","update","watch"]},{"name":"clustergenerators/status","singularName":"clustergenerator","namespaced":false,"group":"secrets.infisical.com","version":"v1alpha1","kind":"ClusterGenerator","verbs":["get","patch","update"]},{"name":"infisicaldynamicsecrets","singularName":"infisicaldynamicsecret","namespaced":true,"group":"secrets.infisical.com","version":"v1alpha1","kind":"InfisicalDynamicSecret","verbs":["delete","deletecollection","get","list","patch","create","update","watch"]},{"name":"infisicaldynamicsecrets/status","singularName":"infisicaldynamicsecret","namespaced":true,"group":"secrets.infisical.com","version":"v1alpha1","kind":"InfisicalDynamicSecret","verbs":["get","patch","update"]},{"name":"infisicalpushsecrets","singularName":"infisicalpushsecret","namespaced":true,"group":"secrets.infisical.com","version":"v1alpha1","kind":"InfisicalPushSecret","verbs":["delete","deletecollection","get","list","patch","create","update","watch"]},{"name":"infisicalpushsecrets/status","singularName":"infisicalpushsecret","namespaced":true,"group":"secrets.infisical.com","version":"v1alpha1","kind":"InfisicalPushSecret","verbs":["get","patch","update"]},{"name":"infisicalsecrets","singularName":"infisicalsecret","namespaced":true,"group":"secrets.infisical.com","version":"v1alpha1","kind":"InfisicalSecret","verbs":["delete","deletecollection","get","list","patch","create","update","watch"]},{"name":"infisicalsecrets/status","singularName":"infisicalsecret","namespaced":true,"group":"secrets.infisical.com","version":"v1alpha1","kind":"InfisicalSecret","verbs":["get","patch","update"]}]}
